README.md
setup.py
locom/__init__.py
locom/annotator.py
locom/base.py
locom/cli.py
locom/parser.py
locom/template.py
locom.egg-info/PKG-INFO
locom.egg-info/SOURCES.txt
locom.egg-info/dependency_links.txt
locom.egg-info/entry_points.txt
locom.egg-info/requires.txt
locom.egg-info/top_level.txt
locom/render/__init__.py
locom/render/abstract.py
locom/render/detail_render.py
locom/render/replacing_render.py
locom/render/row_render.py
locom/template/dark.html
tests/__init__.py
tests/basic_run.py
tests/test_initial.py